evolis/BezelBehavior.py
evolis/CardFace.py
evolis/CardPos.py
evolis/CleaningInfo.py
evolis/Connection.py
evolis/Device.py
evolis/Dpi.py
evolis/ErrorManagement.py
evolis/ErrorManagementLocker.py
evolis/Evolis.py
evolis/Feeder.py
evolis/InputTray.py
evolis/LaminatorFilmInfo.py
evolis/LaminatorFilmType.py
evolis/LaminatorIndex.py
evolis/LaminatorInfo.py
evolis/LaminatorMode.py
evolis/LogLevel.py
evolis/MagCoercivity.py
evolis/MagFormat.py
evolis/MagSession.py
evolis/MagTrackNumber.py
evolis/Mark.py
evolis/Model.py
evolis/OpenMode.py
evolis/OutputTray.py
evolis/PrintSession.py
evolis/PrinterInfo.py
evolis/ReturnCode.py
evolis/RibbonInfo.py
evolis/RibbonType.py
evolis/RwCardType.py
evolis/ScanImage.py
evolis/ScanOption.py
evolis/ScanSession.py
evolis/Service.py
evolis/ServiceAction.py
evolis/SettingKey.py
evolis/State.py
evolis/Status.py
evolis/Type.py
evolis/lib/linux-aarch64/libevolis.so
evolis/lib/linux-armv7-lts/libevolis.so
evolis/lib/linux-x86_64/libevolis.so
evolis/lib/macos/libevolis.dylib
evolis/lib/windows-x86/evolis.dll
evolis/lib/windows-x86_64/evolis.dll
evolis/__init__.py
evolis_sdk-9.2.0.dist-info/METADATA
evolis_sdk-9.2.0.dist-info/WHEEL
evolis_sdk-9.2.0.dist-info/RECORD
