Metadata-Version: 2.4
Name: Evolis-SDK
Version: 9.2.0
Summary: This package is part of the Evolis SDK version 3. Documentation and examples can be found on the Evolis SDK Documentation.
Project-URL: Homepage, https://www2.evolis.com/sdk
Project-URL: Documentation, https://www2.evolis.com/sdk
Author-email: Evolis Card Printer <sdksupport@evolis.com>
Classifier: Operating System :: MacOS :: MacOS X
Classifier: Operating System :: Microsoft :: Windows
Classifier: Operating System :: POSIX :: Linux
Classifier: Programming Language :: Python :: 3
Classifier: Topic :: Printing
Requires-Python: >=3.8
